fitrat/__init__.py
fitrat/language_detector/.gitignore
fitrat/language_detector/LanguageDetector.py
fitrat/language_detector/README.md
fitrat/language_detector/__init__.py
fitrat/language_detector/data/train.txt
fitrat/language_detector/data/valid.txt
fitrat/language_detector/model/langdetect.ftz
fitrat/tokenizers/README.md
fitrat/tokenizers/__init__.py
fitrat/tokenizers/word_tokenize.py
fitrat/transliterators/Transliterator.py
fitrat/transliterators/__init__.py
fitrat/transliterators/utils.py
fitrat/transliterators/cyr_lat/CyrLatTransliterator.py
fitrat/transliterators/cyr_lat/__init__.py
fitrat/transliterators/cyr_lat/alphabet.py
fitrat/transliterators/cyr_lat/model_compile.py
fitrat/transliterators/cyr_lat/model/cyr_lat.hfstol
fitrat/transliterators/lat_cyr/LatCyrTransliterator.py
fitrat/transliterators/lat_cyr/__init__.py
fitrat/transliterators/lat_cyr/alphabet.py
fitrat/transliterators/lat_cyr/model_compile.py
fitrat/transliterators/lat_cyr/data/exceptions.tsv
fitrat/transliterators/lat_cyr/model/exception_pruned.hfstol
fitrat/transliterators/lat_cyr/model/lat_cyr.hfstol
fitrat-0.0.9.dist-info/METADATA
fitrat-0.0.9.dist-info/WHEEL
fitrat-0.0.9.dist-info/licenses/LICENSE
fitrat-0.0.9.dist-info/RECORD
