Metadata-Version: 2.1
Name: fitrat
Version: 0.0.9
Summary: An NLP library for Uzbek. It includes morphological analysis, language identification, transliterators and tokenizers.
Project-URL: Homepage, https://github.com/tahrirchi/fitrat
Project-URL: Bug Tracker, https://github.com/tahrirchi/fitrat/issues
Author-email: Muhammadsaid Mamasaidov <mukhammadsaid.mamasaidov@gmail.com>, Jasur Yusupov <jasuryusupov14@gmail.com>
Maintainer-email: Muhammadsaid Mamasaidov <mukhammadsaid.mamasaidov@gmail.com>, Jasur Yusupov <jasuryusupov14@gmail.com>
License: MIT License
License-File: LICENSE
Keywords: language,morphology,nlp,tahrirchi,transliteration,uzbek
Classifier: License :: OSI Approved :: MIT License
Classifier: Operating System :: POSIX
Classifier: Programming Language :: Python :: 3
Classifier: Topic :: Text Processing :: Linguistic
Requires-Python: >=3.7
Requires-Dist: fasttext==0.9.2
Requires-Dist: hfstol==1.2.11
